transcli/__init__.py
transcli/translate.py
transcli-0.1.1.dist-info/LICENSE
transcli-0.1.1.dist-info/METADATA
transcli-0.1.1.dist-info/WHEEL
transcli-0.1.1.dist-info/entry_points.txt
transcli-0.1.1.dist-info/top_level.txt
transcli-0.1.1.dist-info/RECORD
