Metadata-Version: 2.1
Name: transcli
Version: 0.1.1
Summary: Command line translation tool (CN to EN)
Home-page: https://github.com/louisyoungx/transcli
Author: louisyoungx
Author-email: 1462648167@qq.com
License: UNKNOWN
Project-URL: Bug Tracker, https://github.com/louisyoungx/transcli/issues
Platform: UNKNOWN
Classifier: Programming Language :: Python :: 3
Classifier: License :: OSI Approved :: MIT License
Classifier: Operating System :: OS Independent
Requires-Python: >=3.6
License-File: LICENSE
